{
  "id": 123,
  "revision": 61,
  "skjemanummer": "TS 12-34.56",
  "path": "datafetchertest",
  "title": "Testskjema for datafetcher komponent",
  "display": "wizard",
  "components": [
    {
      "id": "ew2nczm",
      "key": "veiledning",
      "tree": false,
      "type": "panel",
      "input": false,
      "label": "Panel",
      "theme": "default",
      "title": "Veiledning",
      "addons": [],
      "hidden": false,
      "prefix": "",
      "suffix": "",
      "unique": false,
      "dbIndex": false,
      "overlay": {
        "top": "",
        "left": "",
        "style": "",
        "width": "",
        "height": ""
      },
      "tooltip": "",
      "disabled": false,
      "lazyLoad": false,
      "multiple": false,
      "redrawOn": "",
      "tabindex": "",
      "validate": {
        "custom": "",
        "unique": false,
        "multiple": false,
        "required": false,
        "customPrivate": false,
        "strictDateValidation": false
      },
      "autofocus": false,
      "encrypted": false,
      "hideLabel": false,
      "modalEdit": false,
      "protected": false,
      "refreshOn": "",
      "tableView": false,
      "attributes": {},
      "breadcrumb": "default",
      "components": [
        {
          "id": "eamnyh",
          "key": "veiledningstekst",
          "tag": "div",
          "type": "htmlelement",
          "attrs": [],
          "input": false,
          "label": "Veiledningstekst",
          "addons": [],
          "hidden": false,
          "prefix": "",
          "suffix": "",
          "unique": false,
          "content": "<p>Et skjema for å teste vår datafetcher</p>",
          "dbIndex": false,
          "overlay": {
            "top": "",
            "left": "",
            "style": "",
            "width": "",
            "height": ""
          },
          "tooltip": "",
          "disabled": false,
          "multiple": false,
          "redrawOn": "",
          "tabindex": "",
          "validate": {
            "custom": "",
            "unique": false,
            "multiple": false,
            "required": false,
            "customPrivate": false,
            "strictDateValidation": false
          },
          "autofocus": false,
          "encrypted": false,
          "fieldSize": "input--xxl",
          "hideLabel": true,
          "modalEdit": false,
          "protected": false,
          "refreshOn": "",
          "tableView": false,
          "attributes": {},
          "errorLabel": "",
          "persistent": false,
          "properties": {},
          "validateOn": "blur",
          "clearOnHide": true,
          "conditional": {
            "eq": ""
          },
          "customClass": "",
          "description": "",
          "placeholder": "",
          "textDisplay": "form",
          "contentForPdf": "",
          "dataGridLabel": false,
          "labelPosition": "top",
          "showCharCount": false,
          "showWordCount": false,
          "calculateValue": "",
          "calculateServer": false,
          "customConditional": "",
          "allowMultipleMasks": false,
          "customDefaultValue": "",
          "allowCalculateOverride": false
        }
      ],
      "errorLabel": "",
      "persistent": false,
      "properties": {},
      "validateOn": "change",
      "clearOnHide": false,
      "conditional": {
        "eq": ""
      },
      "customClass": "",
      "description": "",
      "placeholder": "",
      "dataGridLabel": false,
      "labelPosition": "top",
      "showCharCount": false,
      "showWordCount": false,
      "calculateValue": "",
      "calculateServer": false,
      "allowMultipleMasks": false,
      "customDefaultValue": "",
      "allowCalculateOverride": false
    },
    {
      "id": "ezemmk",
      "key": "arbeidsrettetaktivitet",
      "tree": false,
      "type": "panel",
      "input": false,
      "label": "Page 4",
      "navId": "e5irvp2",
      "theme": "default",
      "title": "Arbeidsrettet aktivitet",
      "addons": [],
      "hidden": false,
      "prefix": "",
      "suffix": "",
      "unique": false,
      "dbIndex": false,
      "overlay": {
        "top": "",
        "left": "",
        "style": "",
        "width": "",
        "height": ""
      },
      "tooltip": "",
      "disabled": false,
      "lazyLoad": false,
      "multiple": false,
      "redrawOn": "",
      "tabindex": "",
      "validate": {
        "custom": "",
        "unique": false,
        "multiple": false,
        "required": false,
        "customPrivate": false,
        "strictDateValidation": false
      },
      "autofocus": false,
      "encrypted": false,
      "hideLabel": false,
      "modalEdit": false,
      "protected": false,
      "refreshOn": "",
      "tableView": false,
      "attributes": {},
      "breadcrumb": "default",
      "components": [
        {
          "id": "e5ys6xl",
          "key": "aktivitetsvelger",
          "type": "dataFetcher",
          "input": true,
          "label": "Aktivitetsvelger",
          "navId": "e7vr6sc",
          "addons": [],
          "errors": "",
          "hidden": false,
          "prefix": "",
          "suffix": "",
          "unique": false,
          "dbIndex": false,
          "overlay": {
            "top": "",
            "left": "",
            "style": "",
            "width": "",
            "height": ""
          },
          "tooltip": "",
          "disabled": false,
          "multiple": false,
          "redrawOn": "",
          "tabindex": "",
          "validate": {
            "custom": "",
            "unique": false,
            "multiple": false,
            "required": true,
            "customPrivate": false,
            "strictDateValidation": false
          },
          "autofocus": false,
          "encrypted": false,
          "fieldSize": "input--xxl",
          "hideLabel": false,
          "modalEdit": false,
          "protected": false,
          "refreshOn": "",
          "tableView": false,
          "attributes": {},
          "errorLabel": "",
          "persistent": true,
          "properties": {},
          "validateOn": "blur",
          "clearOnHide": true,
          "conditional": {
            "eq": ""
          },
          "customClass": "",
          "description": "",
          "placeholder": "",
          "queryParams": {
            "stønadstype": "BOUTGIFTER"
          },
          "dataGridLabel": false,
          "labelPosition": "top",
          "showCharCount": false,
          "showWordCount": false,
          "calculateValue": "",
          "calculateServer": false,
          "customConditional": "",
          "allowMultipleMasks": false,
          "customDefaultValue": "",
          "allowCalculateOverride": false,
          "additionalDescriptionText": "",
          "additionalDescriptionLabel": ""
        },
        {
          "id": "e0om74h",
          "key": "alertstripe1",
          "type": "alertstripe",
          "input": false,
          "label": "",
          "navId": "e5gkzye",
          "addons": [],
          "hidden": false,
          "prefix": "",
          "suffix": "",
          "unique": false,
          "content": "<p>Kall for å hente aktiviteter feilet</p>",
          "dbIndex": false,
          "overlay": {
            "top": "",
            "left": "",
            "style": "",
            "width": "",
            "height": ""
          },
          "tooltip": "",
          "disabled": false,
          "isInline": false,
          "multiple": false,
          "redrawOn": "",
          "tabindex": "",
          "validate": {
            "custom": "",
            "unique": false,
            "multiple": false,
            "required": false,
            "customPrivate": false,
            "strictDateValidation": false
          },
          "alerttype": "error",
          "autofocus": false,
          "encrypted": false,
          "hideLabel": true,
          "modalEdit": false,
          "protected": false,
          "refreshOn": "",
          "tableView": false,
          "attributes": {},
          "errorLabel": "",
          "persistent": true,
          "properties": {},
          "validateOn": "change",
          "clearOnHide": true,
          "conditional": {
            "eq": ""
          },
          "customClass": "",
          "description": "",
          "placeholder": "",
          "textDisplay": "form",
          "contentForPdf": "",
          "dataGridLabel": false,
          "labelPosition": "top",
          "showCharCount": false,
          "showWordCount": false,
          "calculateValue": "",
          "calculateServer": false,
          "customConditional": "show = utils.dataFetcher('aktivitetsvelger', submission).failure",
          "allowMultipleMasks": false,
          "customDefaultValue": "",
          "allowCalculateOverride": false
        },
        {
          "id": "egkbbv",
          "key": "alertstripe",
          "type": "alertstripe",
          "input": false,
          "label": "",
          "navId": "egmznnv",
          "addons": [],
          "hidden": false,
          "prefix": "",
          "suffix": "",
          "unique": false,
          "content": "<p>Ingen aktiviteter ble hentet</p>",
          "dbIndex": false,
          "overlay": {
            "top": "",
            "left": "",
            "style": "",
            "width": "",
            "height": ""
          },
          "tooltip": "",
          "disabled": false,
          "isInline": false,
          "multiple": false,
          "redrawOn": "",
          "tabindex": "",
          "validate": {
            "custom": "",
            "unique": false,
            "multiple": false,
            "required": false,
            "customPrivate": false,
            "strictDateValidation": false
          },
          "alerttype": "warning",
          "autofocus": false,
          "encrypted": false,
          "hideLabel": true,
          "modalEdit": false,
          "protected": false,
          "refreshOn": "",
          "tableView": false,
          "attributes": {},
          "errorLabel": "",
          "persistent": true,
          "properties": {},
          "validateOn": "change",
          "clearOnHide": true,
          "conditional": {
            "eq": ""
          },
          "customClass": "",
          "description": "",
          "placeholder": "",
          "textDisplay": "form",
          "contentForPdf": "",
          "dataGridLabel": false,
          "labelPosition": "top",
          "showCharCount": false,
          "showWordCount": false,
          "calculateValue": "",
          "calculateServer": false,
          "customConditional": "var dataFetcher = utils.dataFetcher('aktivitetsvelger', submission);\nshow = dataFetcher.fetchDisabled || dataFetcher.empty;",
          "allowMultipleMasks": false,
          "customDefaultValue": "",
          "allowCalculateOverride": false
        },
        {
          "key": "alertstripe2",
          "type": "alertstripe",
          "input": false,
          "label": "",
          "navId": "e8a052k",
          "content": "<p>Du har valgt aktivitet med type TILTAK</p>",
          "isInline": false,
          "tableView": false,
          "textDisplay": "form",
          "customConditional": "show = utils.dataFetcher('aktivitetsvelger', submission).selected({type: 'TILTAK'})",
          "placeholder": "",
          "prefix": "",
          "customClass": "",
          "suffix": "",
          "multiple": false,
          "defaultValue": null,
          "protected": false,
          "unique": false,
          "persistent": true,
          "hidden": false,
          "clearOnHide": true,
          "refreshOn": "",
          "redrawOn": "",
          "modalEdit": false,
          "dataGridLabel": false,
          "labelPosition": "top",
          "description": "",
          "errorLabel": "",
          "tooltip": "",
          "hideLabel": true,
          "tabindex": "",
          "disabled": false,
          "autofocus": false,
          "dbIndex": false,
          "customDefaultValue": "",
          "calculateValue": "",
          "calculateServer": false,
          "widget": null,
          "attributes": {},
          "validateOn": "change",
          "validate": {
            "required": false,
            "custom": "",
            "customPrivate": false,
            "strictDateValidation": false,
            "multiple": false,
            "unique": false
          },
          "conditional": {
            "show": null,
            "when": null,
            "eq": ""
          },
          "overlay": {
            "style": "",
            "left": "",
            "top": "",
            "width": "",
            "height": ""
          },
          "allowCalculateOverride": false,
          "encrypted": false,
          "showCharCount": false,
          "showWordCount": false,
          "properties": {},
          "allowMultipleMasks": false,
          "addons": [],
          "alerttype": "info",
          "id": "eilsxvb",
          "keyModified": true
        }
      ],
      "errorLabel": "",
      "persistent": false,
      "properties": {},
      "validateOn": "change",
      "clearOnHide": false,
      "conditional": {
        "eq": ""
      },
      "customClass": "",
      "description": "",
      "placeholder": "",
      "dataGridLabel": false,
      "labelPosition": "top",
      "showCharCount": false,
      "showWordCount": false,
      "calculateValue": "",
      "calculateServer": false,
      "customConditional": "",
      "isAttachmentPanel": false,
      "allowMultipleMasks": false,
      "customDefaultValue": "",
      "allowCalculateOverride": false
    },
    {
      "id": "e0ii3z",
      "key": "vedlegg",
      "tree": false,
      "type": "panel",
      "input": false,
      "label": "Panel",
      "theme": "default",
      "title": "Vedlegg",
      "addons": [],
      "hidden": false,
      "prefix": "",
      "suffix": "",
      "unique": false,
      "dbIndex": false,
      "overlay": {
        "top": "",
        "left": "",
        "style": "",
        "width": "",
        "height": ""
      },
      "tooltip": "",
      "disabled": false,
      "lazyLoad": false,
      "multiple": false,
      "redrawOn": "",
      "tabindex": "",
      "validate": {
        "custom": "",
        "unique": false,
        "multiple": false,
        "required": false,
        "customPrivate": false,
        "strictDateValidation": false
      },
      "autofocus": false,
      "encrypted": false,
      "hideLabel": false,
      "modalEdit": false,
      "protected": false,
      "refreshOn": "",
      "tableView": false,
      "attributes": {},
      "breadcrumb": "default",
      "components": [
        {
          "description": "<p><span>Hvis du har like utgifter hver måned, holder det å legge ved én faktura.</span></p>",
          "attachmentValues": {
            "leggerVedNaa": {
              "enabled": true,
              "additionalDocumentation": {
                "enabled": false
              }
            },
            "ettersender": {
              "enabled": true,
              "additionalDocumentation": {
                "enabled": false
              },
              "showDeadline": false
            },
            "levertTidligere": {
              "enabled": true,
              "additionalDocumentation": {
                "enabled": false
              }
            },
            "harIkke": {
              "additionalDocumentation": {},
              "enabled": false
            },
            "andre": {
              "additionalDocumentation": {},
              "enabled": false
            },
            "nav": {
              "additionalDocumentation": {},
              "enabled": false
            }
          },
          "customConditional": "show = utils.dataFetcher('aktivitetsvelger', submission).fetchDisabled;",
          "label": "Faktura fra SFO",
          "key": "fakturaFraSfo",
          "input": true,
          "tableView": false,
          "validate": {
            "required": true,
            "custom": "",
            "customPrivate": false,
            "strictDateValidation": false,
            "multiple": false,
            "unique": false
          },
          "properties": {
            "vedleggstittel": "Faktura fra SFO",
            "vedleggskode": "F1"
          },
          "type": "attachment",
          "attachmentType": "default",
          "placeholder": "",
          "prefix": "",
          "customClass": "",
          "suffix": "",
          "multiple": false,
          "defaultValue": null,
          "protected": false,
          "unique": false,
          "persistent": true,
          "hidden": false,
          "clearOnHide": true,
          "refreshOn": "",
          "redrawOn": "",
          "modalEdit": false,
          "dataGridLabel": false,
          "labelPosition": "top",
          "errorLabel": "",
          "tooltip": "",
          "hideLabel": false,
          "tabindex": "",
          "disabled": false,
          "autofocus": false,
          "dbIndex": false,
          "customDefaultValue": "",
          "calculateValue": "",
          "calculateServer": false,
          "widget": null,
          "attributes": {},
          "validateOn": "blur",
          "conditional": {
            "show": null,
            "when": null,
            "eq": ""
          },
          "overlay": {
            "style": "",
            "left": "",
            "top": "",
            "width": "",
            "height": ""
          },
          "allowCalculateOverride": false,
          "encrypted": false,
          "showCharCount": false,
          "showWordCount": false,
          "allowMultipleMasks": false,
          "addons": [],
          "fieldSize": "input--xxl",
          "dataSrc": "values",
          "id": "e0mom7s",
          "keyModified": true
        },
        {
          "id": "ejod5gl",
          "key": "annenDokumentasjon",
          "type": "attachment",
          "input": true,
          "label": "Annen dokumentasjon",
          "addons": [],
          "hidden": false,
          "prefix": "",
          "suffix": "",
          "unique": false,
          "dataSrc": "values",
          "dbIndex": false,
          "overlay": {
            "top": "",
            "left": "",
            "style": "",
            "width": "",
            "height": ""
          },
          "tooltip": "",
          "disabled": false,
          "multiple": false,
          "redrawOn": "",
          "tabindex": "",
          "validate": {
            "custom": "",
            "unique": false,
            "multiple": false,
            "required": true,
            "customPrivate": false,
            "strictDateValidation": false
          },
          "autofocus": false,
          "encrypted": false,
          "fieldSize": "input--xxl",
          "hideLabel": false,
          "modalEdit": false,
          "protected": false,
          "refreshOn": "",
          "tableView": false,
          "attributes": {},
          "errorLabel": "",
          "persistent": true,
          "properties": {
            "vedleggskode": "N6",
            "vedleggstittel": "Annet"
          },
          "validateOn": "blur",
          "clearOnHide": true,
          "conditional": {
            "eq": ""
          },
          "customClass": "",
          "description": "Har du noen annen dokumentasjon du ønsker å legge ved?",
          "placeholder": "",
          "dataGridLabel": false,
          "labelPosition": "top",
          "showCharCount": false,
          "showWordCount": false,
          "attachmentType": "other",
          "calculateValue": "",
          "calculateServer": false,
          "attachmentValues": {
            "nei": {
              "enabled": true
            },
            "leggerVedNaa": {
              "enabled": true
            }
          },
          "allowMultipleMasks": false,
          "customDefaultValue": "",
          "allowCalculateOverride": false
        }
      ],
      "errorLabel": "",
      "persistent": false,
      "properties": {},
      "validateOn": "change",
      "clearOnHide": false,
      "conditional": {
        "eq": ""
      },
      "customClass": "",
      "description": "",
      "placeholder": "",
      "dataGridLabel": false,
      "labelPosition": "top",
      "showCharCount": false,
      "showWordCount": false,
      "calculateValue": "",
      "calculateServer": false,
      "isAttachmentPanel": true,
      "allowMultipleMasks": false,
      "customDefaultValue": "",
      "allowCalculateOverride": false
    }
  ],
  "properties": {
    "tema": "DAG",
    "signatures": [
      {
        "key": "f4dd6fa8-2599-4ab0-ae17-4304dca46db0",
        "label": "",
        "description": ""
      }
    ],
    "submissionTypes": [
      "DIGITAL",
      "PAPER"
    ],
    "ettersendelsesfrist": "14",
    "mellomlagringDurationDays": "28",
    "subsequentSubmissionTypes": [
      "DIGITAL"
    ]
  },
  "createdAt": "2025-02-24T12:39:25.372+01",
  "createdBy": "Mock",
  "changedAt": "2025-04-08T10:29:36.671+02",
  "changedBy": "Mock",
  "status": "draft"
}
