{
  "id": 277,
  "revision": 33,
  "skjemanummer": "phonenumberareacode",
  "path": "phonenumberareacode",
  "title": "Tlfnr",
  "display": "wizard",
  "components": [
    {
      "id": "eterqmr",
      "key": "dineOpplysninger",
      "tree": false,
      "type": "panel",
      "input": false,
      "label": "Panel",
      "theme": "default",
      "title": "Dine opplysninger",
      "addons": [],
      "hidden": false,
      "prefix": "",
      "suffix": "",
      "unique": false,
      "dbIndex": false,
      "overlay": {
        "top": "",
        "left": "",
        "style": "",
        "width": "",
        "height": ""
      },
      "tooltip": "",
      "disabled": false,
      "lazyLoad": false,
      "multiple": false,
      "redrawOn": "",
      "tabindex": "",
      "validate": {
        "custom": "",
        "unique": false,
        "multiple": false,
        "required": false,
        "customPrivate": false,
        "strictDateValidation": false
      },
      "autofocus": false,
      "encrypted": false,
      "hideLabel": false,
      "modalEdit": false,
      "protected": false,
      "refreshOn": "",
      "tableView": false,
      "attributes": {},
      "breadcrumb": "default",
      "components": [
        {
          "key": "telefonnummer1",
          "type": "phoneNumber",
          "input": true,
          "label": "Telefonnummer med landskode",
          "navId": "ewveq0l",
          "validate": {
            "required": true,
            "custom": "",
            "customPrivate": false,
            "strictDateValidation": false,
            "multiple": false,
            "unique": false
          },
          "fieldSize": "input--s",
          "inputMask": false,
          "tableView": false,
          "spellcheck": false,
          "autocomplete": "tel",
          "showAreaCode": true,
          "placeholder": "",
          "prefix": "",
          "customClass": "",
          "suffix": "",
          "multiple": false,
          "defaultValue": null,
          "protected": false,
          "unique": false,
          "persistent": true,
          "hidden": false,
          "clearOnHide": true,
          "refreshOn": "",
          "redrawOn": "",
          "modalEdit": false,
          "dataGridLabel": false,
          "labelPosition": "top",
          "description": "",
          "errorLabel": "",
          "tooltip": "",
          "hideLabel": false,
          "tabindex": "",
          "disabled": false,
          "autofocus": false,
          "dbIndex": false,
          "customDefaultValue": "",
          "calculateValue": "",
          "calculateServer": false,
          "widget": null,
          "attributes": {},
          "validateOn": "blur",
          "conditional": {
            "show": null,
            "when": null,
            "eq": ""
          },
          "overlay": {
            "style": "",
            "left": "",
            "top": "",
            "width": "",
            "height": ""
          },
          "allowCalculateOverride": false,
          "encrypted": false,
          "showCharCount": false,
          "showWordCount": false,
          "properties": {},
          "allowMultipleMasks": false,
          "addons": [],
          "id": "ep1495",
          "keyModified": true
        },
        {
          "id": "emjbrz",
          "key": "telefonnummer2",
          "type": "phoneNumber",
          "input": true,
          "label": "Telefonnummer",
          "navId": "ecqwcl",
          "addons": [],
          "errors": "",
          "hidden": false,
          "prefix": "",
          "suffix": "",
          "unique": false,
          "dbIndex": false,
          "overlay": {
            "top": "",
            "left": "",
            "style": "",
            "width": "",
            "height": ""
          },
          "tooltip": "",
          "disabled": false,
          "multiple": false,
          "redrawOn": "",
          "tabindex": "",
          "validate": {
            "custom": "",
            "unique": false,
            "multiple": false,
            "required": true,
            "maxLength": "",
            "minLength": "",
            "customMessage": "",
            "customPrivate": false,
            "strictDateValidation": false
          },
          "autofocus": false,
          "encrypted": false,
          "fieldSize": "input--s",
          "hideLabel": false,
          "inputMask": false,
          "modalEdit": false,
          "protected": false,
          "refreshOn": "",
          "tableView": false,
          "attributes": {},
          "errorLabel": "",
          "persistent": true,
          "properties": {},
          "spellcheck": false,
          "validateOn": "blur",
          "clearOnHide": true,
          "conditional": {
            "eq": ""
          },
          "customClass": "",
          "description": "",
          "placeholder": "",
          "autocomplete": "tel",
          "showAreaCode": false,
          "dataGridLabel": false,
          "labelPosition": "top",
          "showCharCount": false,
          "showWordCount": false,
          "calculateValue": "",
          "calculateServer": false,
          "customConditional": "",
          "allowMultipleMasks": false,
          "customDefaultValue": "",
          "allowCalculateOverride": false
        },
        {
          "id": "omjbaz",
          "key": "telefonnummer3",
          "type": "phoneNumber",
          "input": true,
          "label": "Telefonnummer ikke påkrevd",
          "navId": "ecqwcl",
          "addons": [],
          "errors": "",
          "hidden": false,
          "prefix": "",
          "suffix": "",
          "unique": false,
          "dbIndex": false,
          "overlay": {
            "top": "",
            "left": "",
            "style": "",
            "width": "",
            "height": ""
          },
          "tooltip": "",
          "disabled": false,
          "multiple": false,
          "redrawOn": "",
          "tabindex": "",
          "validate": {
            "custom": "",
            "unique": false,
            "multiple": false,
            "required": false,
            "maxLength": "",
            "minLength": "",
            "customMessage": "",
            "customPrivate": false,
            "strictDateValidation": false
          },
          "autofocus": false,
          "encrypted": false,
          "fieldSize": "input--s",
          "hideLabel": false,
          "inputMask": false,
          "modalEdit": false,
          "protected": false,
          "refreshOn": "",
          "tableView": false,
          "attributes": {},
          "errorLabel": "",
          "persistent": true,
          "properties": {},
          "spellcheck": false,
          "validateOn": "blur",
          "clearOnHide": true,
          "conditional": {
            "eq": ""
          },
          "customClass": "",
          "description": "",
          "placeholder": "",
          "autocomplete": "tel",
          "showAreaCode": false,
          "dataGridLabel": false,
          "labelPosition": "top",
          "showCharCount": false,
          "showWordCount": false,
          "calculateValue": "",
          "calculateServer": false,
          "customConditional": "",
          "allowMultipleMasks": false,
          "customDefaultValue": "",
          "allowCalculateOverride": false
        }
      ],
      "errorLabel": "",
      "persistent": false,
      "properties": {},
      "validateOn": "change",
      "clearOnHide": false,
      "conditional": {
        "eq": ""
      },
      "customClass": "",
      "description": "",
      "placeholder": "",
      "dataGridLabel": false,
      "labelPosition": "top",
      "showCharCount": false,
      "showWordCount": false,
      "calculateValue": "",
      "calculateServer": false,
      "allowMultipleMasks": false,
      "customDefaultValue": "",
      "allowCalculateOverride": false
    },
    {
      "isAttachmentPanel": false,
      "title": "Telefonnummer og datagrid",
      "key": "telefonnummerOgDatagrid",
      "type": "panel",
      "input": false,
      "label": "Panel",
      "navId": "ex2xbxn",
      "tableView": false,
      "components": [
        {
          "showAreaCode": true,
          "label": "Telefonnummer utenfor datagrid",
          "key": "telefonnummerUtenforDatagrid",
          "type": "phoneNumber",
          "input": true,
          "navId": "et7p76o",
          "fieldSize": "input--s",
          "inputMask": false,
          "tableView": false,
          "spellcheck": false,
          "autocomplete": "tel"
        },
        {
          "key": "datagrid",
          "type": "datagrid",
          "input": true,
          "label": "Repeterende data",
          "navId": "e7gsmco",
          "validate": {
            "required": true
          },
          "tableView": false,
          "components": [
            {
              "showAreaCode": true,
              "label": "Telefonnummer inni datagrid",
              "key": "telefonnummerInniDatagrid",
              "type": "phoneNumber",
              "input": true,
              "navId": "e5yppnj",
              "fieldSize": "input--s",
              "inputMask": false,
              "tableView": false,
              "spellcheck": false,
              "autocomplete": "tel"
            }
          ],
          "validateOn": "blur",
          "isNavDataGrid": true
        }
      ]
    },
    {
      "isAttachmentPanel": false,
      "title": "Validering av skjult telefonnummer",
      "key": "valideringAvSkjultTelefonnummer",
      "label": "Validering av skjult telefonnummer",
      "type": "panel",
      "navId": "ewtpuj8",
      "input": false,
      "tableView": false,
      "components": [
        {
          "validate": {
            "required": true,
            "minLength": "8",
            "custom": "",
            "customPrivate": false,
            "strictDateValidation": false,
            "multiple": false,
            "unique": false
          },
          "conditional": {
            "show": false,
            "when": "harIkkeTelefonnummer",
            "eq": "true"
          },
          "label": "Telefonnummer",
          "key": "telefonnummer4",
          "mask": false,
          "type": "phoneNumber",
          "input": true,
          "navId": "euxuik2",
          "widget": {
            "type": "input"
          },
          "fieldSize": "input--s",
          "inputMask": false,
          "inputMode": "decimal",
          "inputType": "tel",
          "tableView": true,
          "spellcheck": false,
          "inputFormat": "plain",
          "keyModified": true,
          "dataGridLabel": true,
          "truncateMultipleSpaces": false,
          "id": "ebl81zj",
          "placeholder": "",
          "prefix": "",
          "customClass": "",
          "suffix": "",
          "multiple": false,
          "defaultValue": null,
          "protected": false,
          "unique": false,
          "persistent": true,
          "hidden": false,
          "clearOnHide": true,
          "refreshOn": "",
          "redrawOn": "",
          "modalEdit": false,
          "labelPosition": "top",
          "description": "",
          "errorLabel": "",
          "tooltip": "",
          "hideLabel": false,
          "tabindex": "",
          "disabled": false,
          "autofocus": false,
          "dbIndex": false,
          "customDefaultValue": "",
          "calculateValue": "",
          "calculateServer": false,
          "attributes": {},
          "validateOn": "blur",
          "overlay": {
            "style": "",
            "left": "",
            "top": "",
            "width": "",
            "height": ""
          },
          "allowCalculateOverride": false,
          "encrypted": false,
          "showCharCount": false,
          "showWordCount": false,
          "properties": {},
          "allowMultipleMasks": false,
          "addons": []
        },
        {
          "key": "harIkkeTelefonnummer",
          "type": "navCheckbox",
          "input": true,
          "label": "Har ikke telefonnummer",
          "navId": "eqcklrk",
          "inputType": "checkbox",
          "tableView": false,
          "defaultValue": false,
          "dataGridLabel": true,
          "labelPosition": "right",
          "additionalDescription": false,
          "id": "e5ql84",
          "placeholder": "",
          "prefix": "",
          "customClass": "",
          "suffix": "",
          "multiple": false,
          "protected": false,
          "unique": false,
          "persistent": true,
          "hidden": false,
          "clearOnHide": true,
          "refreshOn": "",
          "redrawOn": "",
          "modalEdit": false,
          "description": "",
          "errorLabel": "",
          "tooltip": "",
          "hideLabel": false,
          "tabindex": "",
          "disabled": false,
          "autofocus": false,
          "dbIndex": false,
          "customDefaultValue": "",
          "calculateValue": "",
          "calculateServer": false,
          "widget": null,
          "attributes": {},
          "validateOn": "blur",
          "validate": {
            "required": false,
            "custom": "",
            "customPrivate": false,
            "strictDateValidation": false,
            "multiple": false,
            "unique": false
          },
          "conditional": {
            "show": null,
            "when": null,
            "eq": ""
          },
          "overlay": {
            "style": "",
            "left": "",
            "top": "",
            "width": "",
            "height": ""
          },
          "allowCalculateOverride": false,
          "encrypted": false,
          "showCharCount": false,
          "showWordCount": false,
          "properties": {},
          "allowMultipleMasks": false,
          "addons": [],
          "fieldSize": "input--xxl"
        }
      ],
      "placeholder": "",
      "prefix": "",
      "customClass": "",
      "suffix": "",
      "multiple": false,
      "defaultValue": null,
      "protected": false,
      "unique": false,
      "persistent": false,
      "hidden": false,
      "clearOnHide": false,
      "refreshOn": "",
      "redrawOn": "",
      "modalEdit": false,
      "dataGridLabel": false,
      "labelPosition": "top",
      "description": "",
      "errorLabel": "",
      "tooltip": "",
      "hideLabel": false,
      "tabindex": "",
      "disabled": false,
      "autofocus": false,
      "dbIndex": false,
      "customDefaultValue": "",
      "calculateValue": "",
      "calculateServer": false,
      "widget": null,
      "attributes": {},
      "validateOn": "change",
      "validate": {
        "required": false,
        "custom": "",
        "customPrivate": false,
        "strictDateValidation": false,
        "multiple": false,
        "unique": false
      },
      "conditional": {
        "show": null,
        "when": null,
        "eq": ""
      },
      "overlay": {
        "style": "",
        "left": "",
        "top": "",
        "width": "",
        "height": ""
      },
      "allowCalculateOverride": false,
      "encrypted": false,
      "showCharCount": false,
      "showWordCount": false,
      "properties": {},
      "allowMultipleMasks": false,
      "addons": [],
      "tree": false,
      "lazyLoad": false,
      "theme": "default",
      "breadcrumb": "default",
      "id": "ejg0smh",
      "keyModified": true
    }
  ],
  "properties": {
    "tema": "AGR",
    "isTestForm": true,
    "signatures": [
      {
        "key": "36bc15ec-5926-4f68-8dee-0f96463b3507",
        "label": "",
        "description": ""
      }
    ],
    "skjemanummer": "tlfnr",
    "submissionTypes": [
      "PAPER",
      "DIGITAL"
    ],
    "ettersendelsesfrist": "14",
    "mellomlagringDurationDays": "28",
    "subsequentSubmissionTypes": [
      "PAPER",
      "DIGITAL"
    ]
  },
  "createdAt": "2025-06-25T13:02:36.940+02",
  "createdBy": "Mock",
  "changedAt": "2025-08-05T09:16:28.496+02",
  "changedBy": "Mock",
  "status": "draft"
}
